pfr/__init__.py
pfr/boxscores.py
pfr/decorators.py
pfr/players.py
pfr/teams.py
pfr/utils.py
pfr/finders/__init__.py
pfr/finders/GPF.py
pfr/finders/PSF.py
pfr/utils/__init__.py
pfr/utils/playParsing.py
pfr/utils/utils.py
pfr-0.5.14.dist-info/DESCRIPTION.rst
pfr-0.5.14.dist-info/METADATA
pfr-0.5.14.dist-info/metadata.json
pfr-0.5.14.dist-info/pbr.json
pfr-0.5.14.dist-info/RECORD
pfr-0.5.14.dist-info/top_level.txt
pfr-0.5.14.dist-info/WHEEL
