Metadata-Version: 2.0
Name: pfr
Version: 0.5.14
Summary: Scraping data from pro-football-reference.com
Home-page: https://github.com/mdgoldberg/pfr
Author: Matt Goldberg
Author-email: mgoldberg@college.harvard.edu
License: Apache License 2.0
Platform: UNKNOWN
Requires-Dist: appdirs
Requires-Dist: numexpr
Requires-Dist: numpy
Requires-Dist: pandas
Requires-Dist: pyquery
Requires-Dist: requests
